Topsis-Vivek-102203871/102203871.py
Topsis-Vivek-102203871/__init__.py
Topsis-Vivek-102203871/topsis.py
topsis_vivek_102203871/__init__.py
topsis_vivek_102203871/__main__.py
topsis_vivek_102203871/topsis.py
Topsis_Vivek_102203871-1.0.5.dist-info/LICENSE.txt
Topsis_Vivek_102203871-1.0.5.dist-info/METADATA
Topsis_Vivek_102203871-1.0.5.dist-info/WHEEL
Topsis_Vivek_102203871-1.0.5.dist-info/top_level.txt
Topsis_Vivek_102203871-1.0.5.dist-info/RECORD
