Metadata-Version: 2.1
Name: Topsis-Vivek-102203871
Version: 1.0.5
Summary: A Python package for implementing the Topsis method
Home-page: https://github.com/VivekAttri01/Topsis-Vivek-102203871
Author: Vivek
Author-email: atrivivek001@gmail.com
Classifier: Programming Language :: Python :: 3
Classifier: License :: OSI Approved :: MIT License
Classifier: Operating System :: OS Independent
Requires-Python: >=3.6
License-File: LICENSE.txt
Requires-Dist: numpy
Requires-Dist: pandas
